Workbook

Sheet Dashboard
B2: Kaveri Retail — Profitability Dashboard, FY 2025
B3: Fictional company · 1,000 orders · Jan–Dec 2025 · 12 cities · All amounts in ₹ after discounts
B6: Region: | D6: All | F6: Channel: | H6: All | J6: Category: | L6: All | N6: Discount cap: | P6: 0.2 | Q6: ← Yellow cells can be changed
B8: TOTAL REVENUE | F8: TOTAL PROFIT | J8: PROFIT MARGIN | N8: ORDERS | R8: AVG ORDER VALUE
B9: =Analysis!B9 -> 2746756.2 | F9: =Analysis!B10 -> 666396.25 | J9: =Analysis!B13 -> 0.24261208 | N9: =Analysis!B11 -> 1000 | R9: =Analysis!B12 -> 2746.7562
B12: ="What-if: capping discounts at "&TEXT(DiscountCap,"0%")&" would add up to "&TEXT(Analysis!B17,"₹#,##0")&" profit across "&TEXT(Analysis!B16,"#,##0")&" orders (assumes the same orders still happen)." -> What-if: capping discounts at 20% would add up to ₹30,346 profit across 137 orders (assumes the same orders still happen).
B13: =TEXT(Analysis!B14,"#,##0")&" orders lost money, a total loss of "&TEXT(-Analysis!B15,"₹#,##0")&"." -> 68 orders lost money, a total loss of ₹12,554.
B49: KEY FINDINGS (full year, all data; these do not change with the filters) | L49: RECOMMENDATIONS
B50: 1. Electronics brings 41% of revenue but only 18% of profit (10.9% margin vs 24.3% overall). | L50: 1. Cap Electronics discounts at 20%. Above that, every order lost money.
B51: 2. Every Electronics order discounted above 20% lost money: 66 orders. | L51: 2. In festive sales, put the deeper discounts on Fashion (41% margin) and
B52: 3. Oct–Nov festive sale: the two biggest revenue months, but the lowest margins (19.2%, 20.6%). | L52: Personal Care (34% margin), which can absorb them.
B53: Revenue beat target (103%, 102%); profit reached only 76% and 81% of target. | L53: 3. Report profit vs target every month, not just revenue. On revenue alone,
B54: 4. Online margin is 21.8% vs 27.0% in store: 20% of online orders got discounts above 20%, | L54: October and November looked like the best months of the year.
B55: against 6% of store orders. | L55: Impact: capping all discounts at 20% adds up to ₹30,346 profit a year (about +4.6%).

Sheet MIS Report
A2: Monthly MIS Report — Revenue and Profit vs Target
A3: Kaveri Retail (fictional) · FY 2025 · Targets come from the Targets sheet
A5: Month: | B5: Oct | C5: ← change this | E5: Month number: | F5: =MATCH(B5,Targets!$A$6:$A$17,0) -> 10
A7: 1. Region performance in the selected month
A8: Region | B8: Revenue Actual | C8: Revenue Target | D8: Variance | E8: Revenue Achieved % | F8: Profit Actual | G8: Profit Target | H8: Profit Achieved % | I8: Margin % | J8: Revenue vs Last Month
A9: North | B9: =SUMIFS(Revenue,Region,$A9,OrderMonth,$F$5) -> 56972.3 | C9: =INDEX(Targets!$B$6:$E$17,$F$5,MATCH($A9,Targets!$B$5:$E$5,0)) -> 83000 | D9: =B9-C9 -> -26027.7 | E9: =IF(C9=0,0,B9/C9) -> 0.68641325 | F9: =SUMIFS(Profit,Region,$A9,OrderMonth,$F$5) -> 11532.3 | G9: =INDEX(Targets!$B$22:$E$33,$F$5,MATCH($A9,Targets!$B$21:$E$21,0)) -> 21580 | H9: =IF(G9=0,0,F9/G9) -> 0.53439759 | I9: =IF(B9=0,0,F9/B9) -> 0.20241942 | J9: =IF($F$5=1,"n/a",IFERROR(B9/SUMIFS(Revenue,Region,$A9,OrderMonth,$F$5-1)-1,"n/a")) -> -0.14257679
A10: South | B10: =SUMIFS(Revenue,Region,$A10,OrderMonth,$F$5) -> 115295.2 | C10: =INDEX(Targets!$B$6:$E$17,$F$5,MATCH($A10,Targets!$B$5:$E$5,0)) -> 102000 | D10: =B10-C10 -> 13295.2 | E10: =IF(C10=0,0,B10/C10) -> 1.1303451 | F10: =SUMIFS(Profit,Region,$A10,OrderMonth,$F$5) -> 20445.2 | G10: =INDEX(Targets!$B$22:$E$33,$F$5,MATCH($A10,Targets!$B$21:$E$21,0)) -> 26520 | H10: =IF(G10=0,0,F10/G10) -> 0.77093514 | I10: =IF(B10=0,0,F10/B10) -> 0.17732915 | J10: =IF($F$5=1,"n/a",IFERROR(B10/SUMIFS(Revenue,Region,$A10,OrderMonth,$F$5-1)-1,"n/a")) -> 0.86529668
A11: East | B11: =SUMIFS(Revenue,Region,$A11,OrderMonth,$F$5) -> 46884.25 | C11: =INDEX(Targets!$B$6:$E$17,$F$5,MATCH($A11,Targets!$B$5:$E$5,0)) -> 46000 | D11: =B11-C11 -> 884.25 | E11: =IF(C11=0,0,B11/C11) -> 1.0192228 | F11: =SUMIFS(Profit,Region,$A11,OrderMonth,$F$5) -> 7074.25 | G11: =INDEX(Targets!$B$22:$E$33,$F$5,MATCH($A11,Targets!$B$21:$E$21,0)) -> 11960 | H11: =IF(G11=0,0,F11/G11) -> 0.59149247 | I11: =IF(B11=0,0,F11/B11) -> 0.15088756 | J11: =IF($F$5=1,"n/a",IFERROR(B11/SUMIFS(Revenue,Region,$A11,OrderMonth,$F$5-1)-1,"n/a")) -> -0.23092917
A12: West | B12: =SUMIFS(Revenue,Region,$A12,OrderMonth,$F$5) -> 120729.3 | C12: =INDEX(Targets!$B$6:$E$17,$F$5,MATCH($A12,Targets!$B$5:$E$5,0)) -> 99000 | D12: =B12-C12 -> 21729.3 | E12: =IF(C12=0,0,B12/C12) -> 1.2194879 | F12: =SUMIFS(Profit,Region,$A12,OrderMonth,$F$5) -> 26109.3 | G12: =INDEX(Targets!$B$22:$E$33,$F$5,MATCH($A12,Targets!$B$21:$E$21,0)) -> 25740 | H12: =IF(G12=0,0,F12/G12) -> 1.0143473 | I12: =IF(B12=0,0,F12/B12) -> 0.21626316 | J12: =IF($F$5=1,"n/a",IFERROR(B12/SUMIFS(Revenue,Region,$A12,OrderMonth,$F$5-1)-1,"n/a")) -> 0.8063865
A13: Total | B13: =SUM(B9:B12) -> 339881.05 | C13: =SUM(C9:C12) -> 330000 | D13: =SUM(D9:D12) -> 9881.05 | E13: =IF(C13=0,0,B13/C13) -> 1.0299426 | F13: =SUM(F9:F12) -> 65161.05 | G13: =SUM(G9:G12) -> 85800 | H13: =IF(G13=0,0,F13/G13) -> 0.7594528 | I13: =IF(B13=0,0,F13/B13) -> 0.19171722 | J13: =IF($F$5=1,"n/a",IFERROR(B13/SUMIFS(Revenue,OrderMonth,$F$5-1)-1,"n/a")) -> 0.32738295
A14: ="Summary: in "&B5&", revenue reached "&TEXT(E13,"0%")&" of target and profit reached "&TEXT(H13,"0%")&" of target, at a "&TEXT(I13,"0.0%")&" margin." -> Summary: in Oct, revenue reached 103% of target and profit reached 76% of target, at a 19.2% margin.
A16: 2. Full year by month (all regions)
A17: Month No | B17: Month | C17: Revenue Actual | D17: Revenue Target | E17: Revenue Achieved % | F17: Profit Actual | G17: Profit Target | H17: Profit Achieved % | I17: Margin % | J17: Revenue vs Last Month
A18: 1 | B18: Jan | C18: =SUMIFS(Revenue,OrderMonth,$A18) -> 192915.35 | D18: =Targets!F6 -> 193000 | E18: =IF(D18=0,0,C18/D18) -> 0.9995614 | F18: =SUMIFS(Profit,OrderMonth,$A18) -> 48275.35 | G18: =Targets!F22 -> 50180 | H18: =IF(G18=0,0,F18/G18) -> 0.96204364 | I18: =IF(C18=0,0,F18/C18) -> 0.2502411 | J18: ="n/a" -> n/a
A19: 2 | B19: Feb | C19: =SUMIFS(Revenue,OrderMonth,$A19) -> 166335.85 | D19: =Targets!F7 -> 180000 | E19: =IF(D19=0,0,C19/D19) -> 0.92408806 | F19: =SUMIFS(Profit,OrderMonth,$A19) -> 49145.85 | G19: =Targets!F23 -> 46800 | H19: =IF(G19=0,0,F19/G19) -> 1.050125 | I19: =IF(C19=0,0,F19/C19) -> 0.29546156 | J19: =IF(C18=0,"n/a",C19/C18-1) -> -0.13777805
A20: 3 | B20: Mar | C20: =SUMIFS(Revenue,OrderMonth,$A20) -> 218425.95 | D20: =Targets!F8 -> 207000 | E20: =IF(D20=0,0,C20/D20) -> 1.0551978 | F20: =SUMIFS(Profit,OrderMonth,$A20) -> 59735.95 | G20: =Targets!F24 -> 53820 | H20: =IF(G20=0,0,F20/G20) -> 1.109921 | I20: =IF(C20=0,0,F20/C20) -> 0.27348376 | J20: =IF(C19=0,"n/a",C20/C19-1) -> 0.3131622
A21: 4 | B21: Apr | C21: =SUMIFS(Revenue,OrderMonth,$A21) -> 174660.2 | D21: =Targets!F9 -> 187000 | E21: =IF(D21=0,0,C21/D21) -> 0.93401176 | F21: =SUMIFS(Profit,OrderMonth,$A21) -> 46600.2 | G21: =Targets!F25 -> 48620 | H21: =IF(G21=0,0,F21/G21) -> 0.95845742 | I21: =IF(C21=0,0,F21/C21) -> 0.26680492 | J21: =IF(C20=0,"n/a",C21/C20-1) -> -0.20036882
A22: 5 | B22: May | C22: =SUMIFS(Revenue,OrderMonth,$A22) -> 188356.95 | D22: =Targets!F10 -> 193000 | E22: =IF(D22=0,0,C22/D22) -> 0.97594275 | F22: =SUMIFS(Profit,OrderMonth,$A22) -> 48936.95 | G22: =Targets!F26 -> 50180 | H22: =IF(G22=0,0,F22/G22) -> 0.97522818 | I22: =IF(C22=0,0,F22/C22) -> 0.25980963 | J22: =IF(C21=0,"n/a",C22/C21-1) -> 0.078419411
A23: 6 | B23: Jun | C23: =SUMIFS(Revenue,OrderMonth,$A23) -> 224305.65 | D23: =Targets!F11 -> 207000 | E23: =IF(D23=0,0,C23/D23) -> 1.0836022 | F23: =SUMIFS(Profit,OrderMonth,$A23) -> 56545.65 | G23: =Targets!F27 -> 53820 | H23: =IF(G23=0,0,F23/G23) -> 1.0506438 | I23: =IF(C23=0,0,F23/C23) -> 0.25209196 | J23: =IF(C22=0,"n/a",C23/C22-1) -> 0.19085412
A24: 7 | B24: Jul | C24: =SUMIFS(Revenue,OrderMonth,$A24) -> 196882.7 | D24: =Targets!F12 -> 193000 | E24: =IF(D24=0,0,C24/D24) -> 1.0201176 | F24: =SUMIFS(Profit,OrderMonth,$A24) -> 45402.7 | G24: =Targets!F28 -> 50180 | H24: =IF(G24=0,0,F24/G24) -> 0.90479673 | I24: =IF(C24=0,0,F24/C24) -> 0.23060787 | J24: =IF(C23=0,"n/a",C24/C23-1) -> -0.12225706
A25: 8 | B25: Aug | C25: =SUMIFS(Revenue,OrderMonth,$A25) -> 266956.5 | D25: =Targets!F13 -> 235000 | E25: =IF(D25=0,0,C25/D25) -> 1.1359851 | F25: =SUMIFS(Profit,OrderMonth,$A25) -> 67056.5 | G25: =Targets!F29 -> 61100 | H25: =IF(G25=0,0,F25/G25) -> 1.0974877 | I25: =IF(C25=0,0,F25/C25) -> 0.25118886 | J25: =IF(C24=0,"n/a",C25/C24-1) -> 0.35591649
A26: 9 | B26: Sep | C26: =SUMIFS(Revenue,OrderMonth,$A26) -> 256053.5 | D26: =Targets!F14 -> 235000 | E26: =IF(D26=0,0,C26/D26) -> 1.0895894 | F26: =SUMIFS(Profit,OrderMonth,$A26) -> 60333.5 | G26: =Targets!F30 -> 61100 | H26: =IF(G26=0,0,F26/G26) -> 0.98745499 | I26: =IF(C26=0,0,F26/C26) -> 0.23562849 | J26: =IF(C25=0,"n/a",C26/C25-1) -> -0.04084186
A27: 10 | B27: Oct | C27: =SUMIFS(Revenue,OrderMonth,$A27) -> 339881.05 | D27: =Targets!F15 -> 330000 | E27: =IF(D27=0,0,C27/D27) -> 1.0299426 | F27: =SUMIFS(Profit,OrderMonth,$A27) -> 65161.05 | G27: =Targets!F31 -> 85800 | H27: =IF(G27=0,0,F27/G27) -> 0.7594528 | I27: =IF(C27=0,0,F27/C27) -> 0.19171722 | J27: =IF(C26=0,"n/a",C27/C26-1) -> 0.32738295
A28: 11 | B28: Nov | C28: =SUMIFS(Revenue,OrderMonth,$A28) -> 323564 | D28: =Targets!F16 -> 316000 | E28: =IF(D28=0,0,C28/D28) -> 1.0239367 | F28: =SUMIFS(Profit,OrderMonth,$A28) -> 66744 | G28: =Targets!F32 -> 82160 | H28: =IF(G28=0,0,F28/G28) -> 0.81236611 | I28: =IF(C28=0,0,F28/C28) -> 0.20627758 | J28: =IF(C27=0,"n/a",C28/C27-1) -> -0.048008119
A29: 12 | B29: Dec | C29: =SUMIFS(Revenue,OrderMonth,$A29) -> 198418.55 | D29: =Targets!F17 -> 226000 | E29: =IF(D29=0,0,C29/D29) -> 0.87795819 | F29: =SUMIFS(Profit,OrderMonth,$A29) -> 52458.55 | G29: =Targets!F33 -> 58760 | H29: =IF(G29=0,0,F29/G29) -> 0.89275953 | I29: =IF(C29=0,0,F29/C29) -> 0.26438329 | J29: =IF(C28=0,"n/a",C29/C28-1) -> -0.38677186
B30: FY Total | C30: =SUM(C18:C29) -> 2746756.2 | D30: =SUM(D18:D29) -> 2702000 | E30: =IF(D30=0,0,C30/D30) -> 1.0165641 | F30: =SUM(F18:F29) -> 666396.25 | G30: =SUM(G18:G29) -> 702520 | H30: =IF(G30=0,0,F30/G30) -> 0.94857976 | I30: =IF(C30=0,0,F30/C30) -> 0.24261208
A32: Colour key: green = target met (100%+) · amber = 95–99% · red = below 95%

Sheet Analysis
A1: Analysis tables (these feed the Dashboard; the filters come from the Dashboard)
A3: Filter | B3: Selected | C3: Used in formulas
A4: Region | B4: =Dashboard!$D$6 -> All | C4: =IF(B4="All","*",B4) -> * | D4: "*" means "any value", so "All" includes everything
A5: Channel | B5: =Dashboard!$H$6 -> All | C5: =IF(B5="All","*",B5) -> *
A6: Category | B6: =Dashboard!$L$6 -> All | C6: =IF(B6="All","*",B6) -> *
A8: KPI | B8: Value
A9: Total Revenue | B9: =SUMIFS(Revenue,Region,$C$4,Channel,$C$5,Category,$C$6) -> 2746756.2
A10: Total Profit | B10: =SUMIFS(Profit,Region,$C$4,Channel,$C$5,Category,$C$6) -> 666396.25
A11: Orders | B11: =COUNTIFS(Region,$C$4,Channel,$C$5,Category,$C$6) -> 1000
A12: Average Order Value | B12: =IF(B11=0,0,B9/B11) -> 2746.7562
A13: Profit Margin | B13: =IF(B9=0,0,B10/B9) -> 0.24261208
A14: Loss-making orders | B14: =COUNTIFS(Profit,"<0",Region,$C$4,Channel,$C$5,Category,$C$6) -> 68
A15: Loss on those orders | B15: =SUMIFS(Profit,Profit,"<0",Region,$C$4,Channel,$C$5,Category,$C$6) -> -12554.2
A16: Orders above discount cap | B16: =COUNTIFS(Disc,">"&DiscountCap,Region,$C$4,Channel,$C$5,Category,$C$6) -> 137
A17: Extra profit if discounts capped | B17: =SUMIFS(LostAboveCap,Region,$C$4,Channel,$C$5,Category,$C$6) -> 30345.85
A19: By Region
A20: Region | B20: Revenue | C20: Profit | D20: Margin % | E20: Orders
A21: North | B21: =SUMIFS(Revenue,Region,$A21,Region,$C$4,Channel,$C$5,Category,$C$6) -> 686373.4 | C21: =SUMIFS(Profit,Region,$A21,Region,$C$4,Channel,$C$5,Category,$C$6) -> 174413.4 | D21: =IF(B21=0,0,C21/B21) -> 0.25410862 | E21: =COUNTIFS(Region,$A21,Region,$C$4,Channel,$C$5,Category,$C$6) -> 247
A22: South | B22: =SUMIFS(Revenue,Region,$A22,Region,$C$4,Channel,$C$5,Category,$C$6) -> 860038.4 | C22: =SUMIFS(Profit,Region,$A22,Region,$C$4,Channel,$C$5,Category,$C$6) -> 214298.4 | D22: =IF(B22=0,0,C22/B22) -> 0.24917306 | E22: =COUNTIFS(Region,$A22,Region,$C$4,Channel,$C$5,Category,$C$6) -> 320
A23: East | B23: =SUMIFS(Revenue,Region,$A23,Region,$C$4,Channel,$C$5,Category,$C$6) -> 388874.45 | C23: =SUMIFS(Profit,Region,$A23,Region,$C$4,Channel,$C$5,Category,$C$6) -> 89364.45 | D23: =IF(B23=0,0,C23/B23) -> 0.22980283 | E23: =COUNTIFS(Region,$A23,Region,$C$4,Channel,$C$5,Category,$C$6) -> 135
A24: West | B24: =SUMIFS(Revenue,Region,$A24,Region,$C$4,Channel,$C$5,Category,$C$6) -> 811470 | C24: =SUMIFS(Profit,Region,$A24,Region,$C$4,Channel,$C$5,Category,$C$6) -> 188320 | D24: =IF(B24=0,0,C24/B24) -> 0.23207266 | E24: =COUNTIFS(Region,$A24,Region,$C$4,Channel,$C$5,Category,$C$6) -> 298
A26: By Month
A27: Month No | B27: Month | C27: Revenue | D27: Profit | E27: Margin % | F27: Orders
A28: 1 | B28: Jan | C28: =SUMIFS(Revenue,OrderMonth,$A28,Region,$C$4,Channel,$C$5,Category,$C$6) -> 192915.35 | D28: =SUMIFS(Profit,OrderMonth,$A28,Region,$C$4,Channel,$C$5,Category,$C$6) -> 48275.35 | E28: =IF(C28=0,0,D28/C28) -> 0.2502411 | F28: =COUNTIFS(OrderMonth,$A28,Region,$C$4,Channel,$C$5,Category,$C$6) -> 70
A29: 2 | B29: Feb | C29: =SUMIFS(Revenue,OrderMonth,$A29,Region,$C$4,Channel,$C$5,Category,$C$6) -> 166335.85 | D29: =SUMIFS(Profit,OrderMonth,$A29,Region,$C$4,Channel,$C$5,Category,$C$6) -> 49145.85 | E29: =IF(C29=0,0,D29/C29) -> 0.29546156 | F29: =COUNTIFS(OrderMonth,$A29,Region,$C$4,Channel,$C$5,Category,$C$6) -> 61
A30: 3 | B30: Mar | C30: =SUMIFS(Revenue,OrderMonth,$A30,Region,$C$4,Channel,$C$5,Category,$C$6) -> 218425.95 | D30: =SUMIFS(Profit,OrderMonth,$A30,Region,$C$4,Channel,$C$5,Category,$C$6) -> 59735.95 | E30: =IF(C30=0,0,D30/C30) -> 0.27348376 | F30: =COUNTIFS(OrderMonth,$A30,Region,$C$4,Channel,$C$5,Category,$C$6) -> 78
A31: 4 | B31: Apr | C31: =SUMIFS(Revenue,OrderMonth,$A31,Region,$C$4,Channel,$C$5,Category,$C$6) -> 174660.2 | D31: =SUMIFS(Profit,OrderMonth,$A31,Region,$C$4,Channel,$C$5,Category,$C$6) -> 46600.2 | E31: =IF(C31=0,0,D31/C31) -> 0.26680492 | F31: =COUNTIFS(OrderMonth,$A31,Region,$C$4,Channel,$C$5,Category,$C$6) -> 70
A32: 5 | B32: May | C32: =SUMIFS(Revenue,OrderMonth,$A32,Region,$C$4,Channel,$C$5,Category,$C$6) -> 188356.95 | D32: =SUMIFS(Profit,OrderMonth,$A32,Region,$C$4,Channel,$C$5,Category,$C$6) -> 48936.95 | E32: =IF(C32=0,0,D32/C32) -> 0.25980963 | F32: =COUNTIFS(OrderMonth,$A32,Region,$C$4,Channel,$C$5,Category,$C$6) -> 73
A33: 6 | B33: Jun | C33: =SUMIFS(Revenue,OrderMonth,$A33,Region,$C$4,Channel,$C$5,Category,$C$6) -> 224305.65 | D33: =SUMIFS(Profit,OrderMonth,$A33,Region,$C$4,Channel,$C$5,Category,$C$6) -> 56545.65 | E33: =IF(C33=0,0,D33/C33) -> 0.25209196 | F33: =COUNTIFS(OrderMonth,$A33,Region,$C$4,Channel,$C$5,Category,$C$6) -> 73
A34: 7 | B34: Jul | C34: =SUMIFS(Revenue,OrderMonth,$A34,Region,$C$4,Channel,$C$5,Category,$C$6) -> 196882.7 | D34: =SUMIFS(Profit,OrderMonth,$A34,Region,$C$4,Channel,$C$5,Category,$C$6) -> 45402.7 | E34: =IF(C34=0,0,D34/C34) -> 0.23060787 | F34: =COUNTIFS(OrderMonth,$A34,Region,$C$4,Channel,$C$5,Category,$C$6) -> 73
A35: 8 | B35: Aug | C35: =SUMIFS(Revenue,OrderMonth,$A35,Region,$C$4,Channel,$C$5,Category,$C$6) -> 266956.5 | D35: =SUMIFS(Profit,OrderMonth,$A35,Region,$C$4,Channel,$C$5,Category,$C$6) -> 67056.5 | E35: =IF(C35=0,0,D35/C35) -> 0.25118886 | F35: =COUNTIFS(OrderMonth,$A35,Region,$C$4,Channel,$C$5,Category,$C$6) -> 79
A36: 9 | B36: Sep | C36: =SUMIFS(Revenue,OrderMonth,$A36,Region,$C$4,Channel,$C$5,Category,$C$6) -> 256053.5 | D36: =SUMIFS(Profit,OrderMonth,$A36,Region,$C$4,Channel,$C$5,Category,$C$6) -> 60333.5 | E36: =IF(C36=0,0,D36/C36) -> 0.23562849 | F36: =COUNTIFS(OrderMonth,$A36,Region,$C$4,Channel,$C$5,Category,$C$6) -> 78
A37: 10 | B37: Oct | C37: =SUMIFS(Revenue,OrderMonth,$A37,Region,$C$4,Channel,$C$5,Category,$C$6) -> 339881.05 | D37: =SUMIFS(Profit,OrderMonth,$A37,Region,$C$4,Channel,$C$5,Category,$C$6) -> 65161.05 | E37: =IF(C37=0,0,D37/C37) -> 0.19171722 | F37: =COUNTIFS(OrderMonth,$A37,Region,$C$4,Channel,$C$5,Category,$C$6) -> 142
A38: 11 | B38: Nov | C38: =SUMIFS(Revenue,OrderMonth,$A38,Region,$C$4,Channel,$C$5,Category,$C$6) -> 323564 | D38: =SUMIFS(Profit,OrderMonth,$A38,Region,$C$4,Channel,$C$5,Category,$C$6) -> 66744 | E38: =IF(C38=0,0,D38/C38) -> 0.20627758 | F38: =COUNTIFS(OrderMonth,$A38,Region,$C$4,Channel,$C$5,Category,$C$6) -> 125
A39: 12 | B39: Dec | C39: =SUMIFS(Revenue,OrderMonth,$A39,Region,$C$4,Channel,$C$5,Category,$C$6) -> 198418.55 | D39: =SUMIFS(Profit,OrderMonth,$A39,Region,$C$4,Channel,$C$5,Category,$C$6) -> 52458.55 | E39: =IF(C39=0,0,D39/C39) -> 0.26438329 | F39: =COUNTIFS(OrderMonth,$A39,Region,$C$4,Channel,$C$5,Category,$C$6) -> 78
A42: By Category
A43: Category | B43: Revenue | C43: Profit | D43: Margin % | E43: Orders | F43: Share of Revenue | G43: Share of Profit
A44: Electronics | B44: =SUMIFS(Revenue,Category,$A44,Region,$C$4,Channel,$C$5,Category,$C$6) -> 1128133.2 | C44: =SUMIFS(Profit,Category,$A44,Region,$C$4,Channel,$C$5,Category,$C$6) -> 122443.25 | D44: =IF(B44=0,0,C44/B44) -> 0.10853616 | E44: =COUNTIFS(Category,$A44,Region,$C$4,Channel,$C$5,Category,$C$6) -> 330 | F44: =IF($B$9=0,0,B44/$B$9) -> 0.41071473 | G44: =IF($B$10=0,0,C44/$B$10) -> 0.1837394
A45: Fashion | B45: =SUMIFS(Revenue,Category,$A45,Region,$C$4,Channel,$C$5,Category,$C$6) -> 620498.7 | C45: =SUMIFS(Profit,Category,$A45,Region,$C$4,Channel,$C$5,Category,$C$6) -> 255038.7 | D45: =IF(B45=0,0,C45/B45) -> 0.41102213 | E45: =COUNTIFS(Category,$A45,Region,$C$4,Channel,$C$5,Category,$C$6) -> 288 | F45: =IF($B$9=0,0,B45/$B$9) -> 0.22590235 | G45: =IF($B$10=0,0,C45/$B$10) -> 0.38271329
A46: Home & Kitchen | B46: =SUMIFS(Revenue,Category,$A46,Region,$C$4,Channel,$C$5,Category,$C$6) -> 696588.65 | C46: =SUMIFS(Profit,Category,$A46,Region,$C$4,Channel,$C$5,Category,$C$6) -> 187698.65 | D46: =IF(B46=0,0,C46/B46) -> 0.26945407 | E46: =COUNTIFS(Category,$A46,Region,$C$4,Channel,$C$5,Category,$C$6) -> 203 | F46: =IF($B$9=0,0,B46/$B$9) -> 0.2536041 | G46: =IF($B$10=0,0,C46/$B$10) -> 0.28166222
A47: Personal Care | B47: =SUMIFS(Revenue,Category,$A47,Region,$C$4,Channel,$C$5,Category,$C$6) -> 301535.65 | C47: =SUMIFS(Profit,Category,$A47,Region,$C$4,Channel,$C$5,Category,$C$6) -> 101215.65 | D47: =IF(B47=0,0,C47/B47) -> 0.33566728 | E47: =COUNTIFS(Category,$A47,Region,$C$4,Channel,$C$5,Category,$C$6) -> 179 | F47: =IF($B$9=0,0,B47/$B$9) -> 0.10977882 | G47: =IF($B$10=0,0,C47/$B$10) -> 0.15188508
A50: By Channel
A51: Channel | B51: Revenue | C51: Profit | D51: Margin % | E51: Orders | F51: Orders above 20% discount
A52: Online | B52: =SUMIFS(Revenue,Channel,$A52,Region,$C$4,Channel,$C$5,Category,$C$6) -> 1456726.4 | C52: =SUMIFS(Profit,Channel,$A52,Region,$C$4,Channel,$C$5,Category,$C$6) -> 317866.4 | D52: =IF(B52=0,0,C52/B52) -> 0.21820597 | E52: =COUNTIFS(Channel,$A52,Region,$C$4,Channel,$C$5,Category,$C$6) -> 556 | F52: =COUNTIFS(Channel,$A52,Disc,">0.2",Region,$C$4,Channel,$C$5,Category,$C$6) -> 112
A53: Store | B53: =SUMIFS(Revenue,Channel,$A53,Region,$C$4,Channel,$C$5,Category,$C$6) -> 1290029.9 | C53: =SUMIFS(Profit,Channel,$A53,Region,$C$4,Channel,$C$5,Category,$C$6) -> 348529.85 | D53: =IF(B53=0,0,C53/B53) -> 0.27017193 | E53: =COUNTIFS(Channel,$A53,Region,$C$4,Channel,$C$5,Category,$C$6) -> 444 | F53: =COUNTIFS(Channel,$A53,Disc,">0.2",Region,$C$4,Channel,$C$5,Category,$C$6) -> 25
A56: By Discount Band
A57: Discount Band | B57: Orders | C57: Revenue | D57: Profit | E57: Margin % | F57: Profit per Order
A58: No discount | B58: =COUNTIFS(Band,$A58,Region,$C$4,Channel,$C$5,Category,$C$6) -> 194 | C58: =SUMIFS(Revenue,Band,$A58,Region,$C$4,Channel,$C$5,Category,$C$6) -> 592117 | D58: =SUMIFS(Profit,Band,$A58,Region,$C$4,Channel,$C$5,Category,$C$6) -> 206277 | E58: =IF(C58=0,0,D58/C58) -> 0.34837203 | F58: =IF(B58=0,0,D58/B58) -> 1063.2835
A59: 1-10% | B59: =COUNTIFS(Band,$A59,Region,$C$4,Channel,$C$5,Category,$C$6) -> 422 | C59: =SUMIFS(Revenue,Band,$A59,Region,$C$4,Channel,$C$5,Category,$C$6) -> 1267861.1 | D59: =SUMIFS(Profit,Band,$A59,Region,$C$4,Channel,$C$5,Category,$C$6) -> 338201.05 | E59: =IF(C59=0,0,D59/C59) -> 0.2667493 | F59: =IF(B59=0,0,D59/B59) -> 801.42429
A60: 11-20% | B60: =COUNTIFS(Band,$A60,Region,$C$4,Channel,$C$5,Category,$C$6) -> 247 | C60: =SUMIFS(Revenue,Band,$A60,Region,$C$4,Channel,$C$5,Category,$C$6) -> 609172.05 | D60: =SUMIFS(Profit,Band,$A60,Region,$C$4,Channel,$C$5,Category,$C$6) -> 113762.05 | E60: =IF(C60=0,0,D60/C60) -> 0.18674864 | F60: =IF(B60=0,0,D60/B60) -> 460.5751
A61: 21-30% | B61: =COUNTIFS(Band,$A61,Region,$C$4,Channel,$C$5,Category,$C$6) -> 124 | C61: =SUMIFS(Revenue,Band,$A61,Region,$C$4,Channel,$C$5,Category,$C$6) -> 257158.75 | D61: =SUMIFS(Profit,Band,$A61,Region,$C$4,Channel,$C$5,Category,$C$6) -> 10008.75 | E61: =IF(C61=0,0,D61/C61) -> 0.038920511 | F61: =IF(B61=0,0,D61/B61) -> 80.715726
A62: Above 30% | B62: =COUNTIFS(Band,$A62,Region,$C$4,Channel,$C$5,Category,$C$6) -> 13 | C62: =SUMIFS(Revenue,Band,$A62,Region,$C$4,Channel,$C$5,Category,$C$6) -> 20447.4 | D62: =SUMIFS(Profit,Band,$A62,Region,$C$4,Channel,$C$5,Category,$C$6) -> -1852.6 | E62: =IF(C62=0,0,D62/C62) -> -0.090603206 | F62: =IF(B62=0,0,D62/B62) -> -142.50769
A65: By Product
A66: Product | B66: Category | C66: Revenue | D66: Profit | E66: Margin % | F66: Orders
A67: Wireless Earbuds | B67: Electronics | C67: =SUMIFS(Revenue,Product,$A67,Region,$C$4,Channel,$C$5,Category,$C$6) -> 255072.4 | D67: =SUMIFS(Profit,Product,$A67,Region,$C$4,Channel,$C$5,Category,$C$6) -> 30432.4 | E67: =IF(C67=0,0,D67/C67) -> 0.11930887 | F67: =COUNTIFS(Product,$A67,Region,$C$4,Channel,$C$5,Category,$C$6) -> 84
A68: Smart Watch | B68: Electronics | C68: =SUMIFS(Revenue,Product,$A68,Region,$C$4,Channel,$C$5,Category,$C$6) -> 418130.5 | D68: =SUMIFS(Profit,Product,$A68,Region,$C$4,Channel,$C$5,Category,$C$6) -> 46880.5 | E68: =IF(C68=0,0,D68/C68) -> 0.1121193 | F68: =COUNTIFS(Product,$A68,Region,$C$4,Channel,$C$5,Category,$C$6) -> 89
A69: Power Bank | B69: Electronics | C69: =SUMIFS(Revenue,Product,$A69,Region,$C$4,Channel,$C$5,Category,$C$6) -> 142305.45 | D69: =SUMIFS(Profit,Product,$A69,Region,$C$4,Channel,$C$5,Category,$C$6) -> 13305.45 | E69: =IF(C69=0,0,D69/C69) -> 0.09349923 | F69: =COUNTIFS(Product,$A69,Region,$C$4,Channel,$C$5,Category,$C$6) -> 77
A70: Bluetooth Speaker | B70: Electronics | C70: =SUMIFS(Revenue,Product,$A70,Region,$C$4,Channel,$C$5,Category,$C$6) -> 312624.9 | D70: =SUMIFS(Profit,Product,$A70,Region,$C$4,Channel,$C$5,Category,$C$6) -> 31824.9 | E70: =IF(C70=0,0,D70/C70) -> 0.10179899 | F70: =COUNTIFS(Product,$A70,Region,$C$4,Channel,$C$5,Category,$C$6) -> 80
A71: Mixer Grinder | B71: Home & Kitchen | C71: =SUMIFS(Revenue,Product,$A71,Region,$C$4,Channel,$C$5,Category,$C$6) -> 295260.5 | D71: =SUMIFS(Profit,Product,$A71,Region,$C$4,Channel,$C$5,Category,$C$6) -> 74760.5 | E71: =IF(C71=0,0,D71/C71) -> 0.25320183 | F71: =COUNTIFS(Product,$A71,Region,$C$4,Channel,$C$5,Category,$C$6) -> 51
A72: Cookware Set | B72: Home & Kitchen | C72: =SUMIFS(Revenue,Product,$A72,Region,$C$4,Channel,$C$5,Category,$C$6) -> 145353.9 | D72: =SUMIFS(Profit,Product,$A72,Region,$C$4,Channel,$C$5,Category,$C$6) -> 43153.9 | E72: =IF(C72=0,0,D72/C72) -> 0.29688849 | F72: =COUNTIFS(Product,$A72,Region,$C$4,Channel,$C$5,Category,$C$6) -> 49
A73: Electric Kettle | B73: Home & Kitchen | C73: =SUMIFS(Revenue,Product,$A73,Region,$C$4,Channel,$C$5,Category,$C$6) -> 84349.65 | D73: =SUMIFS(Profit,Product,$A73,Region,$C$4,Channel,$C$5,Category,$C$6) -> 23509.65 | E73: =IF(C73=0,0,D73/C73) -> 0.27871663 | F73: =COUNTIFS(Product,$A73,Region,$C$4,Channel,$C$5,Category,$C$6) -> 45
A74: Dinner Set | B74: Home & Kitchen | C74: =SUMIFS(Revenue,Product,$A74,Region,$C$4,Channel,$C$5,Category,$C$6) -> 171624.6 | D74: =SUMIFS(Profit,Product,$A74,Region,$C$4,Channel,$C$5,Category,$C$6) -> 46274.6 | E74: =IF(C74=0,0,D74/C74) -> 0.26962685 | F74: =COUNTIFS(Product,$A74,Region,$C$4,Channel,$C$5,Category,$C$6) -> 58
A75: Cotton Kurta | B75: Fashion | C75: =SUMIFS(Revenue,Product,$A75,Region,$C$4,Channel,$C$5,Category,$C$6) -> 84640.85 | D75: =SUMIFS(Profit,Product,$A75,Region,$C$4,Channel,$C$5,Category,$C$6) -> 39060.85 | E75: =IF(C75=0,0,D75/C75) -> 0.46148934 | F75: =COUNTIFS(Product,$A75,Region,$C$4,Channel,$C$5,Category,$C$6) -> 69
A76: Denim Jeans | B76: Fashion | C76: =SUMIFS(Revenue,Product,$A76,Region,$C$4,Channel,$C$5,Category,$C$6) -> 191047.55 | D76: =SUMIFS(Profit,Product,$A76,Region,$C$4,Channel,$C$5,Category,$C$6) -> 82627.55 | E76: =IF(C76=0,0,D76/C76) -> 0.4324973 | F76: =COUNTIFS(Product,$A76,Region,$C$4,Channel,$C$5,Category,$C$6) -> 80
A77: Running Shoes | B77: Fashion | C77: =SUMIFS(Revenue,Product,$A77,Region,$C$4,Channel,$C$5,Category,$C$6) -> 240130.55 | D77: =SUMIFS(Profit,Product,$A77,Region,$C$4,Channel,$C$5,Category,$C$6) -> 88030.55 | E77: =IF(C77=0,0,D77/C77) -> 0.36659455 | F77: =COUNTIFS(Product,$A77,Region,$C$4,Channel,$C$5,Category,$C$6) -> 67
A78: Backpack | B78: Fashion | C78: =SUMIFS(Revenue,Product,$A78,Region,$C$4,Channel,$C$5,Category,$C$6) -> 104679.75 | D78: =SUMIFS(Profit,Product,$A78,Region,$C$4,Channel,$C$5,Category,$C$6) -> 45319.75 | E78: =IF(C78=0,0,D78/C78) -> 0.43293712 | F78: =COUNTIFS(Product,$A78,Region,$C$4,Channel,$C$5,Category,$C$6) -> 72
... A82: Skincare Kit | B82: Personal Care | C82: =SUMIFS(Revenue,Product,$A82,Region,$C$4,Channel,$C$5,Category,$C$6) -> 82161.75 | D82: =SUMIFS(Profit,Product,$A82,Region,$C$4,Channel,$C$5,Category,$C$6) -> 32461.75 | E82: =IF(C82=0,0,D82/C82) -> 0.39509565 | F82: =COUNTIFS(Product,$A82,Region,$C$4,Channel,$C$5,Category,$C$6) -> 46

Sheet Cleaned Data
A1: Order ID | B1: Order Date | C1: Month No | D1: City | E1: Region | F1: Channel | G1: Category | H1: Product | I1: Quantity | J1: Unit Price | K1: Discount % | L1: Unit Cost | M1: Revenue | N1: Cost | O1: Profit | P1: Margin % | Q1: Discount Band | R1: Profit Lost Above Cap
A2: KR-25-0001 | B2: 45674 | C2: =MONTH(B2) -> 1 | D2: Hyderabad | E2: South | F2: Store | G2: Fashion | H2: Backpack | I2: 1 | J2: 1099 | K2: 0 | L2: =VLOOKUP(H2,'Product List'!$A$3:$D$18,4,FALSE()) -> 560 | M2: =I2*J2*(1-K2) -> 1099 | N2: =I2*L2 -> 560 | O2: =M2-N2 -> 539 | P2: =IF(M2=0,0,O2/M2) -> 0.49044586 | Q2: =IF(K2=0,"No discount",IF(K2<=0.1,"1-10%",IF(K2<=0.2,"11-20%",IF(K2<=0.3,"21-30%","Above 30%")))) -> No discount | R2: =I2*J2*MAX(0,K2-DiscountCap) -> 0
A3: KR-25-0002 | B3: 45663 | C3: =MONTH(B3) -> 1 | D3: Ahmedabad | E3: West | F3: Store | G3: Fashion | H3: Denim Jeans | I3: 1 | J3: 1499 | K3: 0 | L3: =VLOOKUP(H3,'Product List'!$A$3:$D$18,4,FALSE()) -> 780 | M3: =I3*J3*(1-K3) -> 1499 | N3: =I3*L3 -> 780 | O3: =M3-N3 -> 719 | P3: =IF(M3=0,0,O3/M3) -> 0.4796531 | Q3: =IF(K3=0,"No discount",IF(K3<=0.1,"1-10%",IF(K3<=0.2,"11-20%",IF(K3<=0.3,"21-30%","Above 30%")))) -> No discount | R3: =I3*J3*MAX(0,K3-DiscountCap) -> 0
A4: KR-25-0003 | B4: 45669 | C4: =MONTH(B4) -> 1 | D4: Kolkata | E4: East | F4: Store | G4: Home & Kitchen | H4: Electric Kettle | I4: 1 | J4: 1199 | K4: 0.1 | L4: =VLOOKUP(H4,'Product List'!$A$3:$D$18,4,FALSE()) -> 780 | M4: =I4*J4*(1-K4) -> 1079.1 | N4: =I4*L4 -> 780 | O4: =M4-N4 -> 299.1 | P4: =IF(M4=0,0,O4/M4) -> 0.27717542 | Q4: =IF(K4=0,"No discount",IF(K4<=0.1,"1-10%",IF(K4<=0.2,"11-20%",IF(K4<=0.3,"21-30%","Above 30%")))) -> 1-10% | R4: =I4*J4*MAX(0,K4-DiscountCap) -> 0
A5: KR-25-0004 | B5: 45683 | C5: =MONTH(B5) -> 1 | D5: Lucknow | E5: North | F5: Online | G5: Electronics | H5: Smart Watch | I5: 2 | J5: 3499 | K5: 0.2 | L5: =VLOOKUP(H5,'Product List'!$A$3:$D$18,4,FALSE()) -> 2750 | M5: =I5*J5*(1-K5) -> 5598.4 | N5: =I5*L5 -> 5500 | O5: =M5-N5 -> 98.4 | P5: =IF(M5=0,0,O5/M5) -> 0.01757645 | Q5: =IF(K5=0,"No discount",IF(K5<=0.1,"1-10%",IF(K5<=0.2,"11-20%",IF(K5<=0.3,"21-30%","Above 30%")))) -> 11-20% | R5: =I5*J5*MAX(0,K5-DiscountCap) -> 0
A6: KR-25-0005 | B6: 45672 | C6: =MONTH(B6) -> 1 | D6: Pune | E6: West | F6: Online | G6: Electronics | H6: Smart Watch | I6: 1 | J6: 3499 | K6: 0.1 | L6: =VLOOKUP(H6,'Product List'!$A$3:$D$18,4,FALSE()) -> 2750 | M6: =I6*J6*(1-K6) -> 3149.1 | N6: =I6*L6 -> 2750 | O6: =M6-N6 -> 399.1 | P6: =IF(M6=0,0,O6/M6) -> 0.12673462 | Q6: =IF(K6=0,"No discount",IF(K6<=0.1,"1-10%",IF(K6<=0.2,"11-20%",IF(K6<=0.3,"21-30%","Above 30%")))) -> 1-10% | R6: =I6*J6*MAX(0,K6-DiscountCap) -> 0
A7: KR-25-0006 | B7: 45678 | C7: =MONTH(B7) -> 1 | D7: Bengaluru | E7: South | F7: Store | G7: Fashion | H7: Denim Jeans | I7: 2 | J7: 1499 | K7: 0 | L7: =VLOOKUP(H7,'Product List'!$A$3:$D$18,4,FALSE()) -> 780 | M7: =I7*J7*(1-K7) -> 2998 | N7: =I7*L7 -> 1560 | O7: =M7-N7 -> 1438 | P7: =IF(M7=0,0,O7/M7) -> 0.4796531 | Q7: =IF(K7=0,"No discount",IF(K7<=0.1,"1-10%",IF(K7<=0.2,"11-20%",IF(K7<=0.3,"21-30%","Above 30%")))) -> No discount | R7: =I7*J7*MAX(0,K7-DiscountCap) -> 0
A8: KR-25-0007 | B8: 45683 | C8: =MONTH(B8) -> 1 | D8: Chennai | E8: South | F8: Online | G8: Fashion | H8: Denim Jeans | I8: 1 | J8: 1499 | K8: 0.15 | L8: =VLOOKUP(H8,'Product List'!$A$3:$D$18,4,FALSE()) -> 780 | M8: =I8*J8*(1-K8) -> 1274.15 | N8: =I8*L8 -> 780 | O8: =M8-N8 -> 494.15 | P8: =IF(M8=0,0,O8/M8) -> 0.38782718 | Q8: =IF(K8=0,"No discount",IF(K8<=0.1,"1-10%",IF(K8<=0.2,"11-20%",IF(K8<=0.3,"21-30%","Above 30%")))) -> 11-20% | R8: =I8*J8*MAX(0,K8-DiscountCap) -> 0
A9: KR-25-0008 | B9: 45671 | C9: =MONTH(B9) -> 1 | D9: Ahmedabad | E9: West | F9: Online | G9: Home & Kitchen | H9: Mixer Grinder | I9: 2 | J9: 3299 | K9: 0 | L9: =VLOOKUP(H9,'Product List'!$A$3:$D$18,4,FALSE()) -> 2250 | M9: =I9*J9*(1-K9) -> 6598 | N9: =I9*L9 -> 4500 | O9: =M9-N9 -> 2098 | P9: =IF(M9=0,0,O9/M9) -> 0.31797514 | Q9: =IF(K9=0,"No discount",IF(K9<=0.1,"1-10%",IF(K9<=0.2,"11-20%",IF(K9<=0.3,"21-30%","Above 30%")))) -> No discount | R9: =I9*J9*MAX(0,K9-DiscountCap) -> 0
A10: KR-25-0009 | B10: 45687 | C10: =MONTH(B10) -> 1 | D10: Hyderabad | E10: South | F10: Online | G10: Electronics | H10: Bluetooth Speaker | I10: 1 | J10: 2499 | K10: 0.2 | L10: =VLOOKUP(H10,'Product List'!$A$3:$D$18,4,FALSE()) -> 1950 | M10: =I10*J10*(1-K10) -> 1999.2 | N10: =I10*L10 -> 1950 | O10: =M10-N10 -> 49.2 | P10: =IF(M10=0,0,O10/M10) -> 0.024609844 | Q10: =IF(K10=0,"No discount",IF(K10<=0.1,"1-10%",IF(K10<=0.2,"11-20%",IF(K10<=0.3,"21-30%","Above 30%")))) -> 11-20% | R10: =I10*J10*MAX(0,K10-DiscountCap) -> 0
A11: KR-25-0010 | B11: 45659 | C11: =MONTH(B11) -> 1 | D11: Hyderabad | E11: South | F11: Store | G11: Home & Kitchen | H11: Mixer Grinder | I11: 2 | J11: 3299 | K11: 0.05 | L11: =VLOOKUP(H11,'Product List'!$A$3:$D$18,4,FALSE()) -> 2250 | M11: =I11*J11*(1-K11) -> 6268.1 | N11: =I11*L11 -> 4500 | O11: =M11-N11 -> 1768.1 | P11: =IF(M11=0,0,O11/M11) -> 0.2820791 | Q11: =IF(K11=0,"No discount",IF(K11<=0.1,"1-10%",IF(K11<=0.2,"11-20%",IF(K11<=0.3,"21-30%","Above 30%")))) -> 1-10% | R11: =I11*J11*MAX(0,K11-DiscountCap) -> 0
A12: KR-25-0011 | B12: 45686 | C12: =MONTH(B12) -> 1 | D12: Bengaluru | E12: South | F12: Store | G12: Fashion | H12: Denim Jeans | I12: 1 | J12: 1499 | K12: 0 | L12: =VLOOKUP(H12,'Product List'!$A$3:$D$18,4,FALSE()) -> 780 | M12: =I12*J12*(1-K12) -> 1499 | N12: =I12*L12 -> 780 | O12: =M12-N12 -> 719 | P12: =IF(M12=0,0,O12/M12) -> 0.4796531 | Q12: =IF(K12=0,"No discount",IF(K12<=0.1,"1-10%",IF(K12<=0.2,"11-20%",IF(K12<=0.3,"21-30%","Above 30%")))) -> No discount | R12: =I12*J12*MAX(0,K12-DiscountCap) -> 0
A13: KR-25-0012 | B13: 45686 | C13: =MONTH(B13) -> 1 | D13: Ahmedabad | E13: West | F13: Online | G13: Electronics | H13: Bluetooth Speaker | I13: 1 | J13: 2499 | K13: 0.1 | L13: =VLOOKUP(H13,'Product List'!$A$3:$D$18,4,FALSE()) -> 1950 | M13: =I13*J13*(1-K13) -> 2249.1 | N13: =I13*L13 -> 1950 | O13: =M13-N13 -> 299.1 | P13: =IF(M13=0,0,O13/M13) -> 0.13298653 | Q13: =IF(K13=0,"No discount",IF(K13<=0.1,"1-10%",IF(K13<=0.2,"11-20%",IF(K13<=0.3,"21-30%","Above 30%")))) -> 1-10% | R13: =I13*J13*MAX(0,K13-DiscountCap) -> 0
... A1001: KR-25-1000 | B1001: 45994 | C1001: =MONTH(B1001) -> 12 | D1001: Kolkata | E1001: East | F1001: Online | G1001: Fashion | H1001: Cotton Kurta | I1001: 1 | J1001: 899 | K1001: 0.1 | L1001: =VLOOKUP(H1001,'Product List'!$A$3:$D$18,4,FALSE()) -> 430 | M1001: =I1001*J1001*(1-K1001) -> 809.1 | N1001: =I1001*L1001 -> 430 | O1001: =M1001-N1001 -> 379.1 | P1001: =IF(M1001=0,0,O1001/M1001) -> 0.4685453 | Q1001: =IF(K1001=0,"No discount",IF(K1001<=0.1,"1-10%",IF(K1001<=0.2,"11-20%",IF(K1001<=0.3,"21-30%","Above 30%")))) -> 1-10% | R1001: =I1001*J1001*MAX(0,K1001-DiscountCap) -> 0

Sheet Raw Data
A1: Order ID | B1: Order Date | C1: City | D1: Region | E1: Channel | F1: Product | G1: Category | H1: Quantity | I1: Unit Price | J1: Discount
A2: KR-25-0001 | B2: 45674 | C2: Hyderabad | D2: South | E2: store | F2: Backpack | G2: Fashion | H2: 1 | I2: 1099 | J2: 0
A3: KR-25-0002 | B3: 45663 | C3: Ahmedabad | D3: West | E3: Store | F3: Denim Jeans | G3: Fashion | H3: 1 | I3: 1499 | J3: 0
A4: KR-25-0003 | B4: 45669 | C4: Kolkata | D4: East | E4: Store | F4: Electric Kettle | G4: Home & Kitchen | H4: 1 | I4: 1199 | J4: 0.1
A5: KR-25-0004 | B5: 45683 | C5: Lucknow | D5: North | E5: Online | F5: Smart Watch | G5: Electronics | H5: 2 | I5: 3499 | J5: 0.2
A6: KR-25-0005 | B6: 45672 | C6: Pune | D6: West | E6: Online | F6: Smart Watch | G6: Electronics | H6: 1 | I6: 3499 | J6: 0.1
A7: KR-25-0006 | B7: 45678 | C7: Bengaluru | D7: South | E7: Store | F7: Denim Jeans | G7: Fashion | H7: 2 | I7: 1499 | J7: 0
A8: KR-25-0007 | B8: 45683 | C8: Chennai | D8: South | E8: Online | F8: Denim Jeans | G8: Fashion | H8: 1 | I8: 1499 | J8: 0.15
A9: KR-25-0008 | B9: 45671 | C9: Ahmedabad | D9: West | E9: Online | F9: Mixer Grinder | G9: Home & Kitchen | H9: 2 | I9: 3299 | J9: 0
A10: KR-25-0009 | B10: 45687 | C10: Hyderabad | D10: South | E10: Online | F10: Bluetooth Speaker | G10: Electronics | H10: 1 | I10: 2499 | J10: 0.2
A11: KR-25-0010 | B11: 45659 | C11: Hyderabad | D11: South | E11: Store | F11: Mixer Grinder | G11: Home & Kitchen | H11: 2 | I11: 3299 | J11: 0.05
A12: KR-25-0011 | B12: 45686 | C12: Bengaluru | D12: South | E12: Store | F12: Denim Jeans | G12: Fashion | H12: 1 | I12: 1499 | J12: 0
A13: KR-25-0012 | B13: 45686 | C13: Ahmedabad | D13: West | E13: Online | F13: Bluetooth Speaker | G13: Electronics | H13: 1 | I13: 2499 | J13: 0.1
... A21: KR-25-0020 | B21: 45676 | C21: Chennai | D21: South | E21: Online | F21: Beard Trimmer | G21: Personal Care | H21: 3 | I21: 1799 | J21: 0.15
A22: KR-25-0021 | B22: 18-01-2025 | C22: Mumbai | D22: West | E22: Store | F22: Smart Watch | G22: Electronics | H22: 2 | I22: 3499 | J22: 0.05
A23: KR-25-0022 | B23: 45667 | C23: Chennai | D23: South | E23: Store | F23: Beard Trimmer | G23: Personal Care | H23: 1 | I23: 1799 | J23: 0
A24: KR-25-0023 | B24: 45673 | C24: Chennai | D24: South | E24: Online | F24: Power Bank | G24: Electronics | H24: 1 | I24: 1299 | J24: 0.15
A25: KR-25-0024 | B25: 45675 | C25: New Delhi | D25: North | E25: Online | F25: Running Shoes | G25: Fashion | H25: 1 | I25: 2299 | J25: 0
A26: KR-25-0025 | B26: 45662 | C26: Hyderabad | D26: South | E26: Online | F26: Cotton Kurta | G26: Fashion | H26: 2 | I26: 899 | J26: 0.2
A27: KR-25-0026 | B27: 45669 | C27: Jaipur | D27: North | E27: Store | F27: Skincare Kit | G27: Personal Care | H27: 2 | I27: 1299 | J27: 0.05
A28: KR-25-0027 | B28: 16-01-2025 | C28: Lucknow | D28: North | E28: Online | F28: Cookware Set | G28: Home & Kitchen | H28: 1 | I28: 2199 | J28: 0.1
A29: KR-25-0028 | B29: 45675 | C29: Patna | D29: East | E29: Store | F29: Bluetooth Speaker | G29: Electronics | H29: 1 | I29: 2499 | J29: 0.05
A30: KR-25-0029 | B30: 45661 | C30: Bhubaneswar | D30: East | E30: Online | F30: Skincare Kit | G30: Personal Care | H30: 2 | I30: 1299 | J30: 0.1
A31: KR-25-0030 | B31: 45660 | C31: Mumbai | D31: West | E31: Online | F31: Smart Watch | G31: Electronics | H31: 1 | I31: 3499 | J31: 0.05
A32: KR-25-0031 | B32: 45682 | C32: Bengaluru | D32: South | E32: Online | F32: Backpack | G32: Fashion | H32: 3 | I32: 1099 | J32: 0.2
A33: KR-25-0032 | B33: 45665 | C33: Jaipur | D33: North | E33: Online | F33: Cotton Kurta | G33: Fashion | H33: 1 | I33: 899 | J33: 0.15
A34: KR-25-0033 | B34: 45680 | C34: Patna | D34: East | E34: Online | F34: Backpack | G34: Fashion | H34: 2 | I34: 1099 | J34: 0
A35: KR-25-0034 | B35: 45668 | C35: Jaipur | D35: North | E35: Online | F35: Electric Kettle | G35: Home & Kitchen | H35: 2 | I35: 1199 | J35: 0.1
A36: KR-25-0035 | B36: 45688 | C36: Ahmedabad | D36: West | E36: Store | F36: Cookware Set | G36: Home & Kitchen | H36: 1 | I36: 2199 | J36: 0.1
A37: KR-25-0036 | B37: 45674 | C37: Chennai | D37: South | E37: Online | F37: Perfume | G37: Personal Care | H37: 1 | I37: 999 | J37: 0.1
A38: KR-25-0037 | B38: 45685 | D38: North | E38: Store | F38: Mixer Grinder | G38: Home & Kitchen | H38: 2 | I38: 3299 | J38: 0.1
A39: KR-25-0038 | B39: 45686 | C39: Bhubaneswar | D39: East | E39: Store | F39: Backpack | G39: Fashion | H39: 2 | I39: 1099 | J39: 0.1
A40: KR-25-0039 | B40: 45668 | C40: Pune | D40: West | E40: Store | F40: Beard Trimmer | G40: Personal Care | H40: 1 | I40: 1799 | J40: 0.15
A41: KR-25-0040 | B41: 45676 | C41: Ahmedabad | D41: West | E41: Online | F41: Bluetooth Speaker | G41: Electronics | H41: 1 | I41: 2499 | J41: 0.15
A42: KR-25-0041 | B42: 45672 | C42: Bengaluru | D42: South | E42: Online | F42: Skincare Kit | G42: Personal Care | H42: 1 | I42: 1299 | J42: 0.2
A43: KR-25-0042 | B43: 45685 | C43: Ahmedabad | D43: West | E43: Online | F43: Cotton Kurta | G43: Fashion | H43: 1 | I43: 899 | J43: 0.1
A44: KR-25-0043 | B44: 45669 | C44: Lucknow | D44: North | E44: Online | F44: Denim Jeans | G44: Fashion | H44: 1 | I44: 1499 | J44: 0.25
A45: KR-25-0044 | B45: 45662 | C45: Mumbai | D45: West | E45: Store | F45: Power Bank | G45: Electronics | H45: 2 | I45: 1299 | J45: 0
A46: KR-25-0045 | B46: 45671 | C46: Pune | D46: West | E46: Online | F46: Cotton Kurta | G46: Fashion | H46: 2 | I46: 899 | J46: 0.05
A47: KR-25-0046 | B47: 45683 | C47: Lucknow | D47: North | E47: Store | F47: Cookware Set | G47: Home & Kitchen | H47: 1 | I47: 2199 | J47: 0
A48: KR-25-0047 | B48: 45669 | D48: South | E48: Store | F48: Cookware Set | G48: Home & Kitchen | H48: 1 | I48: 2199 | J48: 0.15
A49: KR-25-0048 | B49: 45687 | C49: New Delhi | D49: North | E49: Store | F49: Smart Watch | G49: Electronics | H49: 1 | I49: 3499 | J49: 0.05
A50: KR-25-0049 | B50: 45674 | C50: Bhubaneswar | D50: East | E50: Online | F50: Backpack | G50: Fashion | H50: 1 | I50: 1099 | J50: 0
A51: KR-25-0050 | B51: 45673 | C51: Bengaluru | D51: South | E51: Store | F51: Cookware Set | G51: Home & Kitchen | H51: 1 | I51: 2199 | J51: 0
A52: KR-25-0051 | B52: 45687 | C52: Ahmedabad | D52: West | E52: Online | F52: Wireless Earbuds | G52: Electronics | H52: 1 | I52: 1999 | J52: 0.2
A53: KR-25-0052 | B53: 45669 | C53: Pune | D53: West | E53: In-store | F53: Denim Jeans | G53: Fashion | H53: 1 | I53: 1499 | J53: 0
A54: KR-25-0053 | B54: 45686 | C54: Ahmedabad | D54: West | E54: Store | F54: Running Shoes | G54: Fashion | H54: 2 | I54: 2299 | J54: 0
A55: KR-25-0054 | B55: 45659 | C55: Pune | D55: West | E55: Store | F55: Electric Kettle | G55: Home & Kitchen | H55: 2 | I55: 1199 | J55: 0.1
A56: KR-25-0055 | B56: 45677 | C56: New Delhi | D56: North | E56: Online | F56: Cotton Kurta | G56: Fashion | H56: 1 | I56: 899 | J56: 0
A57: KR-25-0056 | B57: 45681 | C57: Jaipur | D57: North | E57: Online | F57: Skincare Kit | G57: Personal Care | H57: 1 | I57: 1299 | J57: 0.15
A58: KR-25-0057 | B58: 45677 | C58: Bengaluru | D58: South | E58: Online | F58: Perfume | G58: Personal Care | H58: 3 | I58: 999 | J58: 0.1
A59: KR-25-0058 | B59: 45668 | C59: Lucknow | D59: North | E59: Online | F59: Wireless Earbuds | G59: Electronics | H59: 3 | I59: 1999 | J59: 0.1
A60: KR-25-0059 | B60: 45671 | C60: Jaipur | D60: North | E60: Store | F60: Denim Jeans | G60: Fashion | H60: 3 | I60: 1499 | J60: 0
A61: KR-25-0060 | B61: 45687 | C61: Hyderabad | D61: South | E61: Online | F61: Cookware Set | G61: Home & Kitchen | H61: 1 | I61: 2199 | J61: 0.15
A62: KR-25-0061 | B62: 19-01-2025 | C62: Ahmedabad | D62: West | E62: Online | F62: Power Bank | G62: Electronics | H62: 2 | I62: 1299 | J62: 0.2
A63: KR-25-0062 | B63: 45662 | C63: Chennai | D63: South | E63: Store | F63: Perfume | G63: Personal Care | H63: 1 | I63: 999 | J63: 0.15
A64: KR-25-0063 | B64: 45672 | C64: New Delhi | D64: North | E64: Store | F64: Smart Watch | G64: Electronics | H64: 3 | I64: 3499 | J64: 0.1
A65: KR-25-0064 | B65: 45683 | C65: Jaipur | D65: North | E65: In-store | F65: Smart Watch | G65: Electronics | H65: 1 | I65: 3499 | J65: 0.15
A66: KR-25-0065 | B66: 45686 | C66: Bengaluru | D66: South | E66: Store | F66: Wireless Earbuds | G66: Electronics | H66: 3 | I66: 1999 | J66: 0.2
A67: KR-25-0066 | B67: 45687 | C67: Bangalore | D67: South | E67: Store | F67: Smart Watch | G67: Electronics | H67: 3 | I67: 3499 | J67: 0.1
A68: KR-25-0067 | B68: 45666 | C68: Lucknow | D68: North | E68: Online | F68: Denim Jeans | G68: Fashion | H68: 1 | I68: 1499 | J68: 0
A69: KR-25-0068 | B69: 45688 | C69: Hyderabad | D69: South | E69: Store | F69: Cookware Set | G69: Home & Kitchen | H69: 3 | I69: 2199 | J69: 0.1
A70: KR-25-0069 | B70: 45674 | C70: Bhubaneswar | D70: East | E70: Online | F70: Cotton Kurta | G70: Fashion | H70: 1 | I70: 899 | J70: 0.2
A71: KR-25-0070 | B71: 45675 | C71: Bengaluru | D71: South | E71: Online | F71: Backpack | G71: Fashion | H71: 1 | I71: 1099 | J71: 0.15
A72: KR-25-0071 | B72: 45691 | C72: Jaipur | D72: North | E72: Store | F72: Face Wash Combo | G72: Personal Care | H72: 2 | I72: 449 | J72: 0.15
A73: KR-25-0072 | B73: 45695 | C73: Chennai | D73: South | E73: Store | F73: Cotton Kurta | G73: Fashion | H73: 2 | I73: 899 | J73: 0.05
A74: KR-25-0073 | B74: 45696 | C74: New Delhi | D74: North | E74: Online | F74: Perfume | G74: Personal Care | H74: 1 | I74: 999 | J74: 0.05
... A108: KR-25-0107 | B108: 45693 | C108: Chennai | D108: South | E108: Store | F108: Denim Jeans | G108: Fashion | H108: 5 | I108: 1499 | J108: 0.05
A109: KR-25-0108 | B109: 45695 | C109: Bengaluru | D109: South | E109: Online | F109: Perfume | H109: 1 | I109: 999 | J109: 0.2
A110: KR-25-0109 | B110: 45691 | C110: Ahmedabad | D110: West | E110: Online | F110: Smart Watch | G110: Electronics | H110: 1 | I110: 3499 | J110: 0.2
A111: KR-25-0110 | B111: 45696 | C111: Pune | D111: West | E111: Store | F111: Running Shoes | G111: Fashion | H111: 1 | I111: 2299 | J111: 0.05
A112: KR-25-0111 | B112: 45708 | C112: Ahmedabad | D112: West | E112: Store | F112: Backpack | G112: Fashion | H112: 2 | I112: 1099 | J112: 0
A113: KR-25-0112 | B113: 45696 | C113: Ahmedabad | D113: West | E113: Online | F113: Running Shoes | G113: Fashion | H113: 1 | I113: 2299 | J113: 0.3
A114: KR-25-0113 | B114: 45700 | C114: Pune | D114: West | E114: Store | F114: Denim Jeans | G114: Fashion | H114: 1 | I114: 1499 | J114: 0.05
A115: KR-25-0114 | B115: 45691 | C115: Kolkata | D115: East | E115: Store | F115: Smart Watch | G115: Electronics | H115: 1 | I115: 3499 | J115: 0.05
A116: KR-25-0115 | B116: 45706 | C116: Chennai | D116: South | E116: Store | F116: Electric Kettle | G116: Home & Kitchen | H116: 1 | I116: 1199 | J116: 0.1
A117: KR-25-0116 | B117: 45700 | C117: Pune | D117: West | E117: Online | F117: Backpack | G117: Fashion | H117: 4 | I117: 1099 | J117: 0.2
A118: KR-25-0117 | B118: 45699 | C118: Lucknow | D118: North | E118: Online | F118: Running Shoes | G118: Fashion | H118: 1 | I118: 2299 | J118: 0.1
A119: KR-25-0118 | B119: 45698 | C119: Hyderabad | D119: South | E119: Store | F119: Bluetooth Speaker | G119: Electronics | H119: 2 | I119: 2499 | J119: 0.1
A120: KR-25-0119 | B120: 45695 | C120: Kolkata | D120: East | E120: Online | F120: Skincare Kit | G120: Personal Care | H120: 1 | I120: 1299 | J120: 0.2
A121: KR-25-0120 | B121: 45694 | C121: Pune | D121: West | E121: Online | F121: Power Bank | G121: Electronics | H121: 2 | I121: 1299 | J121: 0.2
A122: KR-25-0121 | B122: 10-02-2025 | C122: Hyderabad | D122: South | E122: Store | F122: Backpack | G122: Fashion | H122: 1 | I122: 1099 | J122: 0.05
A123: KR-25-0122 | B123: 45705 | C123: Ahmedabad | D123: West | E123: Online | F123: Dinner Set | G123: Home & Kitchen | H123: 2 | I123: 1799 | J123: 0.1
A124: KR-25-0123 | B124: 45694 | C124: Bengaluru | D124: South | E124: Store | F124: Denim Jeans | G124: Fashion | H124: 3 | I124: 1499 | J124: 0
A125: KR-25-0124 | B125: 45695 | C125: Pune | D125: West | E125: Store | F125: Perfume | G125: Personal Care | H125: 2 | I125: 999 | J125: 0.1
A126: KR-25-0125 | B126: 45691 | C126: Hyderabad | D126: South | E126: Store | F126: Power Bank | G126: Electronics | H126: 2 | I126: 1299 | J126: 0.25
A127: KR-25-0126 | B127: 45703 | C127: Kolkata | D127: East | E127: Online | F127: Mixer Grinder | G127: Home & Kitchen | H127: 2 | I127: 3299 | J127: 0.1
A128: KR-25-0127 | B128: 45703 | C128: New Delhi | D128: North | E128: Store | F128: Cotton Kurta | G128: Fashion | H128: 2 | I128: 899 | J128: 0
A129: KR-25-0128 | B129: 45711 | C129: Mumbai | D129: West | E129: Online | F129: Wireless Earbuds | G129: Electronics | H129: 1 | I129: 1999 | J129: 0.15
A130: KR-25-0129 | B130: 45690 | C130: Bengaluru | D130: South | E130: Online | F130: Cotton Kurta | G130: Fashion | H130: 2 | I130: 899 | J130: 0.15
A131: KR-25-0130 | B131: 45716 | C131: Chennai | D131: South | E131: Store | F131: Denim Jeans | G131: Fashion | H131: 2 | I131: 1499 | J131: 0.1
A132: KR-25-0131 | B132: 45709 | C132: Bangalore | D132: South | E132: Store | F132: Electric Kettle | G132: Home & Kitchen | H132: 2 | I132: 1199 | J132: 0
A133: KR-25-0132 | B133: 45743 | C133: Mumbai | D133: West | E133: Online | F133: Backpack | G133: Fashion | H133: 1 | I133: 1099 | J133: 0.1
A134: KR-25-0133 | B134: 45718 | C134: Pune | D134: West | E134: Online | F134: Bluetooth Speaker | G134: Electronics | H134: 1 | I134: 2499 | J134: 0.05
... A172: KR-25-0170 | B172: 45734 | C172: Ahmedabad | D172: West | E172: Online | F172: Backpack | G172: Fashion | H172: 1 | I172: 1099 | J172: 0.15
A173: KR-25-0171 | B173: 45739 | C173: Patna | D173: East | E173: Online | F173: Electric Kettle | G173: Home & Kitchen | H173: 2 | I173: 1199 | J173: 15%
A174: KR-25-0172 | B174: 45722 | C174: New Delhi | D174: North | E174: Online | F174: Dinner Set | G174: Home & Kitchen | H174: 1 | I174: 1799 | J174: 0.15
A175: KR-25-0173 | B175: 45742 | C175: Lucknow | D175: North | E175: Store | F175: Smart Watch | G175: Electronics | H175: 1 | I175: 3499 | J175: 0.1
A176: KR-25-0174 | B176: 45736 | C176: Pune | D176: West | E176: Online | F176: Face Wash Combo | G176: Personal Care | H176: 2 | I176: 449 | J176: 0.3
A177: KR-25-0175 | B177: 45744 | C177: Pune | D177: West | E177: Online | F177: Power Bank | G177: Electronics | H177: 2 | I177: 1299 | J177: 0.05
...

Sheet Product List
A1: Product List (price and cost per unit)
A2: Product | B2: Category | C2: Unit Price (₹) | D2: Unit Cost (₹) | E2: List Margin %
A3: Wireless Earbuds | B3: Electronics | C3: 1999 | D3: 1560 | E3: =(C3-D3)/C3 -> 0.2196098
A4: Smart Watch | B4: Electronics | C4: 3499 | D4: 2750 | E4: =(C4-D4)/C4 -> 0.21406116
A5: Power Bank | B5: Electronics | C5: 1299 | D5: 1000 | E5: =(C5-D5)/C5 -> 0.23017706
A6: Bluetooth Speaker | B6: Electronics | C6: 2499 | D6: 1950 | E6: =(C6-D6)/C6 -> 0.21968788
A7: Mixer Grinder | B7: Home & Kitchen | C7: 3299 | D7: 2250 | E7: =(C7-D7)/C7 -> 0.31797514
A8: Cookware Set | B8: Home & Kitchen | C8: 2199 | D8: 1400 | E8: =(C8-D8)/C8 -> 0.36334698
A9: Electric Kettle | B9: Home & Kitchen | C9: 1199 | D9: 780 | E9: =(C9-D9)/C9 -> 0.34945788
A10: Dinner Set | B10: Home & Kitchen | C10: 1799 | D10: 1150 | E10: =(C10-D10)/C10 -> 0.36075598
A11: Cotton Kurta | B11: Fashion | C11: 899 | D11: 430 | E11: =(C11-D11)/C11 -> 0.52169077
A12: Denim Jeans | B12: Fashion | C12: 1499 | D12: 780 | E12: =(C12-D12)/C12 -> 0.4796531
A13: Running Shoes | B13: Fashion | C13: 2299 | D13: 1300 | E13: =(C13-D13)/C13 -> 0.43453676
A14: Backpack | B14: Fashion | C14: 1099 | D14: 560 | E14: =(C14-D14)/C14 -> 0.49044586
... A18: Skincare Kit | B18: Personal Care | C18: 1299 | D18: 700 | E18: =(C18-D18)/C18 -> 0.46112394
A20: Blue numbers are inputs. Margin % is before any discount.

Sheet Targets
A1: FY2025 Targets (company plan)
A2: Fictional plan set for this project. Blue numbers are inputs; change them and every report updates.
A3: Planned profit margin | B3: 0.26
A4: Revenue target (₹)
A5: Month | B5: North | C5: South | D5: East | E5: West | F5: Total
A6: Jan | B6: 48000 | C6: 60000 | D6: 27000 | E6: 58000 | F6: =SUM(B6:E6) -> 193000
A7: Feb | B7: 45000 | C7: 56000 | D7: 25000 | E7: 54000 | F7: =SUM(B7:E7) -> 180000
A8: Mar | B8: 52000 | C8: 64000 | D8: 29000 | E8: 62000 | F8: =SUM(B8:E8) -> 207000
A9: Apr | B9: 47000 | C9: 58000 | D9: 26000 | E9: 56000 | F9: =SUM(B9:E9) -> 187000
A10: May | B10: 48000 | C10: 60000 | D10: 27000 | E10: 58000 | F10: =SUM(B10:E10) -> 193000
A11: Jun | B11: 52000 | C11: 64000 | D11: 29000 | E11: 62000 | F11: =SUM(B11:E11) -> 207000
A12: Jul | B12: 48000 | C12: 60000 | D12: 27000 | E12: 58000 | F12: =SUM(B12:E12) -> 193000
A13: Aug | B13: 59000 | C13: 73000 | D13: 33000 | E13: 70000 | F13: =SUM(B13:E13) -> 235000
A14: Sep | B14: 59000 | C14: 73000 | D14: 33000 | E14: 70000 | F14: =SUM(B14:E14) -> 235000
A15: Oct | B15: 83000 | C15: 102000 | D15: 46000 | E15: 99000 | F15: =SUM(B15:E15) -> 330000
A16: Nov | B16: 79000 | C16: 98000 | D16: 44000 | E16: 95000 | F16: =SUM(B16:E16) -> 316000
A17: Dec | B17: 56000 | C17: 70000 | D17: 32000 | E17: 68000 | F17: =SUM(B17:E17) -> 226000
A18: Total | B18: =SUM(B6:B17) -> 676000 | C18: =SUM(C6:C17) -> 838000 | D18: =SUM(D6:D17) -> 378000 | E18: =SUM(E6:E17) -> 810000 | F18: =SUM(F6:F17) -> 2702000
A20: Profit target (₹) = revenue target × planned margin
A21: Month | B21: North | C21: South | D21: East | E21: West | F21: Total
A22: Jan | B22: =B6*$B$3 -> 12480 | C22: =C6*$B$3 -> 15600 | D22: =D6*$B$3 -> 7020 | E22: =E6*$B$3 -> 15080 | F22: =SUM(B22:E22) -> 50180
A23: Feb | B23: =B7*$B$3 -> 11700 | C23: =C7*$B$3 -> 14560 | D23: =D7*$B$3 -> 6500 | E23: =E7*$B$3 -> 14040 | F23: =SUM(B23:E23) -> 46800
A24: Mar | B24: =B8*$B$3 -> 13520 | C24: =C8*$B$3 -> 16640 | D24: =D8*$B$3 -> 7540 | E24: =E8*$B$3 -> 16120 | F24: =SUM(B24:E24) -> 53820
A25: Apr | B25: =B9*$B$3 -> 12220 | C25: =C9*$B$3 -> 15080 | D25: =D9*$B$3 -> 6760 | E25: =E9*$B$3 -> 14560 | F25: =SUM(B25:E25) -> 48620
A26: May | B26: =B10*$B$3 -> 12480 | C26: =C10*$B$3 -> 15600 | D26: =D10*$B$3 -> 7020 | E26: =E10*$B$3 -> 15080 | F26: =SUM(B26:E26) -> 50180
A27: Jun | B27: =B11*$B$3 -> 13520 | C27: =C11*$B$3 -> 16640 | D27: =D11*$B$3 -> 7540 | E27: =E11*$B$3 -> 16120 | F27: =SUM(B27:E27) -> 53820
A28: Jul | B28: =B12*$B$3 -> 12480 | C28: =C12*$B$3 -> 15600 | D28: =D12*$B$3 -> 7020 | E28: =E12*$B$3 -> 15080 | F28: =SUM(B28:E28) -> 50180
A29: Aug | B29: =B13*$B$3 -> 15340 | C29: =C13*$B$3 -> 18980 | D29: =D13*$B$3 -> 8580 | E29: =E13*$B$3 -> 18200 | F29: =SUM(B29:E29) -> 61100
A30: Sep | B30: =B14*$B$3 -> 15340 | C30: =C14*$B$3 -> 18980 | D30: =D14*$B$3 -> 8580 | E30: =E14*$B$3 -> 18200 | F30: =SUM(B30:E30) -> 61100
A31: Oct | B31: =B15*$B$3 -> 21580 | C31: =C15*$B$3 -> 26520 | D31: =D15*$B$3 -> 11960 | E31: =E15*$B$3 -> 25740 | F31: =SUM(B31:E31) -> 85800
A32: Nov | B32: =B16*$B$3 -> 20540 | C32: =C16*$B$3 -> 25480 | D32: =D16*$B$3 -> 11440 | E32: =E16*$B$3 -> 24700 | F32: =SUM(B32:E32) -> 82160
A33: Dec | B33: =B17*$B$3 -> 14560 | C33: =C17*$B$3 -> 18200 | D33: =D17*$B$3 -> 8320 | E33: =E17*$B$3 -> 17680 | F33: =SUM(B33:E33) -> 58760
A34: Total | B34: =SUM(B22:B33) -> 175760 | C34: =SUM(C22:C33) -> 217880 | D34: =SUM(D22:D33) -> 98280 | E34: =SUM(E22:E33) -> 210600 | F34: =SUM(F22:F33) -> 702520

Sheet Cleaning Log
A1: Cleaning Log: how the raw data became the cleaned data
A2: Rows received: 1,012 → Clean orders: 1,000
A4: Step | B4: Problem found | C4: Rows affected | D4: What I did | E4: Excel feature used
A5: 1 | B5: Same order entered twice (exact duplicate rows) | C5: 12 | D5: Removed the duplicate copies, kept one of each | E5: Data > Remove Duplicates
A6: 2 | B6: Channel spelled differently: "online", "ONLINE", "Store ", "In-store" | C6: 64 | D6: Standardised to two values: "Online" and "Store" | E6: TRIM, PROPER, Find & Replace
A7: 3 | B7: City spelled differently ("Bangalore" in 38 rows, lower case, extra spaces) | C7: 60 | D7: Standardised city names; "Bangalore" changed to "Bengaluru" | E7: TRIM, PROPER, Find & Replace
A8: 4 | B8: City missing | C8: 6 | D8: Set to "Unknown". Region was present, so the orders were kept | E8: Filter > (Blanks)
A9: 5 | B9: Category missing | C9: 9 | D9: Filled in from the Product List using the product name | E9: VLOOKUP
A10: 6 | B10: Discount typed as text (e.g. "15%"), so it could not be calculated | C10: 25 | D10: Converted to numbers | E10: VALUE / Text to Columns
A11: 7 | B11: Order date typed as text (dd-mm-yyyy), so Excel could not group it by month | C11: 18 | D11: Converted to real dates | E11: Text to Columns (DMY)
A13: Steps 2–7 were counted after removing duplicates. Revenue, cost, profit and margin are calculated with formulas in the Cleaned Data sheet, not typed in.
